{
  "name": "Flutter",
  "description": "Flutter fork template",
  "categories": ["Mobile"],
  "icon": "https://www.gstatic.com/images/branding/productlogos/flutter/v6/192px.svg",
  "publisher": "Rody Davis",
  "host": {
    "virtualization": "true"
  },
  "params": [
    {
      "id": "template",
      "name": "Template",
      "type": "enum",
      "default": "app",
      "options": {
        "app": "App",
        "module": "Module",
        "package": "Package",
        "plugin": "Plugin",
        "plugin_ffi": "Plugin (FFI)",
        "skeleton": "Skeleton"
      }
    },
    {
      "id": "repo",
      "name": "Git Repo",
      "type": "text",
      "default": "https://github.com/flutter/flutter"
    },
    {
      "id": "branch",
      "name": "Git Branch",
      "type": "text",
      "default": "stable"
    }
  ]
}
